vanta/__init__.py
vanta-0.0.1.dist-info/WHEEL
vanta-0.0.1.dist-info/METADATA
vanta-0.0.1.dist-info/RECORD
