Metadata-Version: 2.1
Name: vanta
Version: 0.0.1
Summary: Blacker than black
License: MIT
Author: Dan Palmer
Author-email: dan@danpalmer.me
Requires-Python: >=3.6,<4.0
Classifier: License :: OSI Approved :: MIT License
Classifier: Programming Language :: Python :: 3
Classifier: Programming Language :: Python :: 3.6
Classifier: Programming Language :: Python :: 3.7
Classifier: Programming Language :: Python :: 3.8
Requires-Dist: black (>=19.10b0,<20.0)
Requires-Dist: flake8-bugbear (>=20.1.4,<21.0.0)
Requires-Dist: flake8-builtins (>=1.5.2,<2.0.0)
Requires-Dist: flake8-coding (>=1.3.2,<2.0.0)
Requires-Dist: flake8-commas (>=2.0.0,<3.0.0)
Requires-Dist: flake8-comprehensions (>=3.2.2,<4.0.0)
Requires-Dist: flake8-debugger (>=3.2.1,<4.0.0)
Requires-Dist: flake8-deprecated (>=1.3,<2.0)
Requires-Dist: flake8-fixme (>=1.1.1,<2.0.0)
Requires-Dist: flake8-isort (>=3.0.0,<4.0.0)
Requires-Dist: flake8-mutable (>=1.2.0,<2.0.0)
Requires-Dist: flake8-pep3101 (>=1.3.0,<2.0.0)
Requires-Dist: flake8-tidy-imports (>=4.1.0,<5.0.0)
Requires-Dist: flake8-tuple (>=0.4.1,<0.5.0)
Requires-Dist: isort (>=4.3.21,<5.0.0)
